{
  "projects": [
    {
      "name": "Webjog",
      "description": "Web app",
      "stack": ["Vue", "Firebase"],
      "githubUrl": "https://github.com/kumpmati/webjog",
      "url": "https://webjog-86a58.firebaseapp.com/"
    },
    {
      "name": "Color My Keyboard",
      "description": "Control the LEDs in my RGB keyboard in realtime",
      "stack": ["Firebase"],
      "githubUrl": "https://github.com/kumpmati/color-my-keyboard",
      "url": "https://colormykeyboard.xyz/"
    },
    {
      "name": "Cahum",
      "description": "Custom version of the 'Cards Against Humanity' game",
      "stack": ["React"],
      "githubUrl": "https://github.com/kumpmati/cards-against-humanists",
      "url": "https://cahum.xyz"
    },
    {
      "name": "Nopsa",
      "description": "UTU transcript of study records PDF analyser",
      "stack": ["Svelte"],
      "githubUrl": "https://github.com/kumpmati/nopsa",
      "url": "https://kumpmati.github.io/nopsa"
    }
  ]
}
